foxglove/py.typed
foxglove/client/__init__.py
foxglove/client/api.py
foxglove_client-0.18.1.dist-info/licenses/LICENSE
foxglove_client-0.18.1.dist-info/METADATA
foxglove_client-0.18.1.dist-info/WHEEL
foxglove_client-0.18.1.dist-info/top_level.txt
foxglove_client-0.18.1.dist-info/RECORD
