Metadata-Version: 2.4
Name: foxglove-client
Version: 0.18.1
Summary: Client library for the Foxglove API.
Home-page: https://github.com/foxglove/foxglove-python
Classifier: Programming Language :: Python :: 3
Classifier: License :: OSI Approved :: MIT License
Classifier: Operating System :: OS Independent
Requires-Python: >=3.7
License-File: LICENSE
Requires-Dist: arrow
Requires-Dist: requests
Requires-Dist: typing_extensions
Requires-Dist: mcap>=1.1.0
Dynamic: license-file
